CHANGELOG
MANIFEST.in
README.rst
setup.py
pyil/__init__.py
pyil/util.py
pyil/enum/modifiable.py
pyil/enum/variable.py
pyil/file/__init__.py
pyil/file/__util.py
pyil/file/file.py
pyil/shared/_coll/Class.py
pyil/shared/_coll/__init__.py
pyil/shared/_coll/error.py
pyil/shared/_coll/method.py
pyil/shared/threading/__init__.py
pyil/shared/threading/__launcher.py
pyil/shared/threading/lock.py
pyil/shared/threading/thread.py
pyil_converter.egg-info/PKG-INFO
pyil_converter.egg-info/SOURCES.txt
pyil_converter.egg-info/dependency_links.txt
pyil_converter.egg-info/requires.txt
pyil_converter.egg-info/top_level.txt
resources/lxml-3.6.4-cp34-cp34m-win32.whl
resources/lxml-3.6.4-cp34-cp34m-win_amd64.whl
resources/lxml-3.6.4-cp35-cp35m-win32.whl
resources/lxml-3.6.4-cp35-cp35m-win_amd64.whl
resources/reinstall.bat