Metadata-Version: 1.1
Name: pyil-converter
Version: 0.6.6.8
Summary: Convert files to the format you want!
Home-page: https://wasted123.github.io/pyil/
Author: G.M
Author-email: G.Mpydev@gmail.com
License: MIT
Keywords: file,format,extension,reformatting,converting,data
Platform: win32
Classifier: Development Status :: 3 - Alpha
Classifier: Programming Language :: Python :: 3 :: Only
Classifier: Operating System :: Microsoft :: Windows
Classifier: Intended Audience :: Developers
Classifier: Intended Audience :: Information Technology
Classifier: Natural Language :: English
Classifier: Topic :: System :: Filesystems
Classifier: Topic :: System :: Archiving :: Packaging
Classifier: Topic :: Utilities
Classifier: License :: OSI Approved :: MIT License
